<?xml version="1.0" encoding="utf-8"?>
<root>
	<ODBCList>
		<Word name="ABSOLUTE"/>
		<Word name="ACTION"/>
		<Word name="ADD"/>
		<Word name="ALL"/>
		<Word name="ALLOCATE"/>
		<Word name="ALTER"/>
		<Word name="AND"/>
		<Word name="ANY"/>
		<Word name="ARE"/>
		<Word name="AS"/>
		<Word name="ASC"/>
		<Word name="ASSERTION"/>
		<Word name="AT"/>
		<Word name="AUTHORIZATION"/>
		<Word name="AVG"/>
		<Word name="BEGIN"/>
		<Word name="BETWEEN"/>
		<Word name="BINARY"/>
		<Word name="BIT"/>
		<Word name="BIT_LENGTH"/>
		<Word name="BLOB"/>
		<Word name="BOOLEAN"/>
		<Word name="BOTH"/>
		<Word name="BY"/>
		<Word name="CASCADE"/>
		<Word name="CASCADED"/>
		<Word name="CASE"/>
		<Word name="CAST"/>
		<Word name="CATALOG"/>
		<Word name="CHAR"/>
		<Word name="CHARACTER"/>
		<Word name="CHARACTER_LENGTH"/>
		<Word name="CHAR_LENGTH"/>
		<Word name="CHECK"/>
		<Word name="CHR"/>
		<Word name="CLOSE"/>
		<Word name="COALESCE"/>
		<Word name="COLLATE"/>
		<Word name="COLLATION"/>
		<Word name="COLUMN"/>
		<Word name="COMMIT"/>
		<Word name="CONNECT"/>
		<Word name="CONNECTION"/>
		<Word name="CONSTRAINT"/>
		<Word name="CONSTRAINTS"/>
		<Word name="CONTINUE"/>
		<Word name="CONVERT"/>
		<Word name="CORRESPONDING"/>
		<Word name="COUNT"/>
		<Word name="CREATE"/>
		<Word name="CROSS"/>
		<Word name="CURDATE"/>
		<Word name="CURRENT"/>
		<Word name="CURRENT_DATE"/>
		<Word name="CURRENT_TIME"/>
		<Word name="CURRENT_TIMESTAMP"/>
		<Word name="CURRENT_USER"/>
		<Word name="CURSOR"/>
		<Word name="CURTIME"/>
		<Word name="CURTIMESTAMP"/>
		<Word name="DATE"/>
		<Word name="DATEVAL"/>
		<Word name="DAY"/>
		<Word name="DAYNAME"/>
		<Word name="DAYOFWEEK"/>
		<Word name="DEALLOCATE"/>
		<Word name="DEC"/>
		<Word name="DECIMAL"/>
		<Word name="DECLARE"/>
		<Word name="DEFAULT"/>
		<Word name="DEFERRABLE"/>
		<Word name="DEFERRED"/>
		<Word name="DELETE"/>
		<Word name="DESC"/>
		<Word name="DESCRIBE"/>
		<Word name="DESCRIPTOR"/>
		<Word name="DIAGNOSTICS"/>
		<Word name="DISCONNECT"/>
		<Word name="DISTINCT"/>
		<Word name="DOMAIN"/>
		<Word name="DOUBLE"/>
		<Word name="DROP"/>
		<Word name="ELSE"/>
		<Word name="END"/>
		<Word name="END_EXEC"/>
		<Word name="ESCAPE"/>
		<Word name="EVERY"/>
		<Word name="EXCEPT"/>
		<Word name="EXCEPTION"/>
		<Word name="EXEC"/>
		<Word name="EXECUTE"/>
		<Word name="EXISTS"/>
		<Word name="EXTERNAL"/>
		<Word name="EXTRACT"/>
		<Word name="FALSE"/>
		<Word name="FETCH"/>
		<Word name="FIRST"/>
		<Word name="FLOAT"/>
		<Word name="FOR"/>
		<Word name="FOREIGN"/>
		<Word name="FOUND"/>
		<Word name="FROM"/>
		<Word name="FULL"/>
		<Word name="GET"/>
		<Word name="GLOBAL"/>
		<Word name="GO"/>
		<Word name="GOTO"/>
		<Word name="GRANT"/>
		<Word name="GROUP"/>
		<Word name="HAVING"/>
		<Word name="HOUR"/>
		<Word name="IDENTITY"/>
		<Word name="IMMEDIATE"/>
		<Word name="IN"/>
		<Word name="INDEX"/>
		<Word name="INDICATOR"/>
		<Word name="INITIALLY"/>
		<Word name="INNER"/>
		<Word name="INPUT"/>
		<Word name="INSENSITIVE"/>
		<Word name="INT"/>
		<Word name="INTEGER"/>
		<Word name="INTERSECT"/>
		<Word name="INTERVAL"/>
		<Word name="INTO"/>
		<Word name="IS"/>
		<Word name="ISOLATION"/>
		<Word name="JOIN"/>
		<Word name="KEY"/>
		<Word name="LANGUAGE"/>
		<Word name="LAST"/>
		<Word name="LEADING"/>
		<Word name="LEFT"/>
		<Word name="LENGTH"/>
		<Word name="LEVEL"/>
		<Word name="LIKE"/>
		<Word name="LOCAL"/>
		<Word name="LONGVARBINARY"/>
		<Word name="LOWER"/>
		<Word name="LTRIM"/>
		<Word name="MATCH"/>
		<Word name="MAX"/>
		<Word name="MIN"/>
		<Word name="MINUTE"/>
		<Word name="MODULE"/>
		<Word name="MONTH"/>
		<Word name="MONTHNAME"/>
		<Word name="NAMES"/>
		<Word name="NATIONAL"/>
		<Word name="NATURAL"/>
		<Word name="NCHAR"/>
		<Word name="NEXT"/>
		<Word name="NO"/>
		<Word name="NOT"/>
		<Word name="NSERT"/>
		<Word name="NULL"/>
		<Word name="NULLIF"/>
		<Word name="NUMERIC"/>
		<Word name="NUMVAL"/>
		<Word name="OCTET_LENGTH"/>
		<Word name="OF"/>
		<Word name="ON"/>
		<Word name="ONLY"/>
		<Word name="OPEN"/>
		<Word name="OPTION"/>
		<Word name="OR"/>
		<Word name="ORDER"/>
		<Word name="OUTER"/>
		<Word name="OUTPUT"/>
		<Word name="OVERLAPS"/>
		<Word name="PAD"/>
		<Word name="PART"/>
		<Word name="PARTIAL"/>
		<Word name="POSITION"/>
		<Word name="PRECISION"/>
		<Word name="PREPARE"/>
		<Word name="PRESERVE"/>
		<Word name="PRIMARY"/>
		<Word name="PRIOR"/>
		<Word name="PRIVILEGES"/>
		<Word name="PROCEDURE"/>
		<Word name="PUBLIC"/>
		<Word name="READ"/>
		<Word name="REAL"/>
		<Word name="REFERENCES"/>
		<Word name="RELATIVE"/>
		<Word name="RESTRICT"/>
		<Word name="REVOKE"/>
		<Word name="RIGHT"/>
		<Word name="ROLLBACK"/>
		<Word name="ROUND"/>
		<Word name="ROWID"/>
		<Word name="ROWS"/>
		<Word name="RTRIM"/>
		<Word name="SCHEMA"/>
		<Word name="SCROLL"/>
		<Word name="SECOND"/>
		<Word name="SECTION"/>
		<Word name="SELECT"/>
		<Word name="SESSION"/>
		<Word name="SESSION_USER"/>
		<Word name="SET"/>
		<Word name="SIZE"/>
		<Word name="SMALLINT"/>
		<Word name="SOME"/>
		<Word name="SPACE"/>
		<Word name="SQL"/>
		<Word name="SQLCODE"/>
		<Word name="SQLERROR"/>
		<Word name="SQLSTATE"/>
		<Word name="STRVAL"/>
		<Word name="SUBSTRING"/>
		<Word name="SUM"/>
		<Word name="SYSTEM_USER"/>
		<Word name="TABLE"/>
		<Word name="TEMPORARY"/>
		<Word name="THEN"/>
		<Word name="TIME"/>
		<Word name="TIMESTAMP"/>
		<Word name="TIMESTAMPVAL"/>
		<Word name="TIMEVAL"/>
		<Word name="TIMEZONE_HOUR"/>
		<Word name="TIMEZONE_MINUTE"/>
		<Word name="TO"/>
		<Word name="TODAY"/>
		<Word name="TRAILING"/>
		<Word name="TRANSACTION"/>
		<Word name="TRANSLATE"/>
		<Word name="TRANSLATION"/>
		<Word name="TRIM"/>
		<Word name="TRUE"/>
		<Word name="UNION"/>
		<Word name="UNIQUE"/>
		<Word name="UNKNOWN"/>
		<Word name="UPDATE"/>
		<Word name="UPPER"/>
		<Word name="USAGE"/>
		<Word name="USAGE"/>
		<Word name="USER"/>
		<Word name="USER"/>
		<Word name="USERNAME"/>
		<Word name="USERNAME"/>
		<Word name="USING"/>
		<Word name="USING"/>
		<Word name="VALUE"/>
		<Word name="VALUES"/>
		<Word name="VARBINARY"/>
		<Word name="VARCHAR"/>
		<Word name="VARYING"/>
		<Word name="VIEW"/>
		<Word name="WHEN"/>
		<Word name="WHENEVER"/>
		<Word name="WHERE"/>
		<Word name="WITH"/>
		<Word name="WORK"/>
		<Word name="WRITE"/>
		<Word name="YEAR"/>
		<Word name="ZONE"/>
	</ODBCList>
</root>
